{"name": "alpaco", "lat": 46.11585251230784, "lon": 12.324489843775968, "pic": "pic/alpaco.jpg"}
{"name": "beitou", "lat": 25.134998602572367, "lon": 121.50688371298513, "pic": "pic/beitou.jpg"}
{"name": "Berlin", "lat": 52.520433, "lon": 13.399413, "pic": "pic/prova2.jpg"}
{"name": "brugge het brembos5", "lat": 51.17413970255977, "lon": 3.2193134141284285, "pic": "pic/brugge_het_brembos5.jpg"}
{"name": "Cape_of_good_hope", "lat": -34.3568182, "lon": 18.4741398, "pic": "pic/CapeofGoodHope.jpg"}
{"name": "freiburg", "lat": 47.99244977633733, "lon": 7.848674019385537, "pic": "pic/freiburg.jpg"}
{"name": "gif_sur_yvette", "lat": 48.70973276199095, "lon": 2.165916580231984, "pic": "pic/gif_sur_yvette.jpg"}
{"name": "ginevra", "lat": 46.26184803373837, "lon": 6.160150020618249, "pic": "pic/ginevra.jpg"}
{"name": "kampot", "lat": 10.61060718504962, "lon": 104.18151933934661, "pic": "pic/kampot.jpg"}
{"name": "landgraaf", "lat": 50.90660545227959, "lon": 6.024083977126442, "pic": "pic/landgraaf.jpg"}
{"name": "mindhoek", "lat": -22.568898191017706, "lon": 17.087413362269587, "pic": "pic/mindhoek.jpg"}
{"name": "oberkirch", "lat": 48.530912980405255, "lon": 8.079144826144448, "pic": "pic/oberkirch.jpg"}
{"name": "oven", "lat": -33.9457107, "lon": 18.8873165, "pic": "pic/ovenStellenbosch.jpg"}
{"name": "palus_san_marco", "lat": 46.53711839015198, "lon": 12.297334680170517, "pic": "pic/palus_san_marco.jpg"}
{"name": "pecs", "lat": 46.07817884281677, "lon": 18.223476873939287, "pic": "pic/pecs.jpg"}
{"name": "Place des Vosges", "lat": 48.855013, "lon": 2.366114, "pic": "pic/prova.jpg"}
{"name": "pula", "lat": 44.8747700270836, "lon": 13.84818154503741, "pic": "pic/pula.jpg"}
{"name": "ribeirao_petro", "lat": -21.1749501, "lon": -47.7962576, "pic": "pic/ribeirao_petro.jpg"}
{"name": "san_paolo", "lat": -23.515300570966634, "lon": -46.765230886245426, "pic": "pic/san_paolo.jpg"}
{"name": "Stellenbosch_campus", "lat": -33.9330322, "lon": 18.8640395, "pic": "pic/stellenbosch.jpg"}
{"name": "villa_vicencio", "lat": 4.1514821, "lon": -73.6382141, "pic": "pic/villa_vicencio.jpg"}
{"name": "villaverla", "lat": 45.65111070310364, "lon": 11.49082474498641, "pic": "pic/villaverla.jpg"}
{"name": "wismar", "lat": 53.898608932609605, "lon": 11.455648886717897, "pic": "pic/wismar.jpg"}
